{
  "total": 164151,
  "last24h": 6882,
  "recentTxs": [
    {
      "hash": "0xc11ae642a4c9be2a655958609ca26bbe979a6d3c3e09cdbc100b4c8761d82723",
      "from": "0xE26155ddBf45748f95F644B1F4AF6c2285E52830",
      "value": "0",
      "blockNumber": 39636326,
      "timeStamp": 1774019662
    },
    {
      "hash": "0x804ce8339156872da2ae2a3800a0bf80e5ad5c3f75baa8f8290ae30e02b67986",
      "from": "0xB70F532a681A8AA3aAC4A0F6bc40bc3384272F58",
      "value": "0",
      "blockNumber": 39636315,
      "timeStamp": 1774019640
    },
    {
      "hash": "0x38ddd9a1db93f3c6d36e1f076f145b6563991755af00606116d67d9b5a7c6420",
      "from": "0x92879E3E5D4F8ddb291cFEAF2F6D33eB5Ec7e0c9",
      "value": "0",
      "blockNumber": 39636301,
      "timeStamp": 1774019615
    },
    {
      "hash": "0x27f900fd0af1a1827dbc9bb3dffa745de80d3807ae325c920821204b3cc5c558",
      "from": "0x27877De4427A41bA19D204ab824b0BeeDDC6bCd6",
      "value": "0",
      "blockNumber": 39636285,
      "timeStamp": 1774019581
    },
    {
      "hash": "0x503b692e66fa0566a8ae45d498c5f7b8eaae61c84eb33967a65ea6e4e5d6e2d9",
      "from": "0x27877De4427A41bA19D204ab824b0BeeDDC6bCd6",
      "value": "0",
      "blockNumber": 39636281,
      "timeStamp": 1774019574
    },
    {
      "hash": "0xb41b452593e281092c7845415cd9bceaf75803a77fefa6fb023dfc58fff22cfe",
      "from": "0x8d636a0e27eE26f8373798B9BEC1f39B38E62511",
      "value": "0",
      "blockNumber": 39636271,
      "timeStamp": 1774019556
    },
    {
      "hash": "0x055aed769194356040aee79ac40abcf82cfd2b0bd389ae0d57b991cd330d99c2",
      "from": "0x0fCf2d37bF3Ab7Ad6b0783354DC764feAEC6a91E",
      "value": "0",
      "blockNumber": 39636261,
      "timeStamp": 1774019536
    },
    {
      "hash": "0x9c6a59f87cbbbb366ac8399002343eef6e516887592b63ffdf7c10ae68e0292e",
      "from": "0xb9E109873e2bC954d64975960657b8cadCb910C4",
      "value": "0",
      "blockNumber": 39636250,
      "timeStamp": 1774019515
    },
    {
      "hash": "0xdf044b84844e89e207afcdfaaeaf2721697585c2fe3d93e28f54646b9894ad02",
      "from": "0x0A76962c08973616F37F7bB68C5527afD1dC5074",
      "value": "0",
      "blockNumber": 39636228,
      "timeStamp": 1774019481
    },
    {
      "hash": "0xa543afad756fd2979137650653cb2dab5cd65ed844a51d76bc07b4992fab11e7",
      "from": "0x0A76962c08973616F37F7bB68C5527afD1dC5074",
      "value": "0",
      "blockNumber": 39636224,
      "timeStamp": 1774019473
    }
  ],
  "lastUpdated": "2026-03-20T15:15:24.378Z",
  "dailyCounts": [
    {
      "date": "2026-03-20",
      "count": 2700
    },
    {
      "date": "2026-03-19",
      "count": 4182
    },
    {
      "date": "2026-03-18",
      "count": 4434
    },
    {
      "date": "2026-03-17",
      "count": 4407
    },
    {
      "date": "2026-03-16",
      "count": 4276
    },
    {
      "date": "2026-03-15",
      "count": 4437
    },
    {
      "date": "2026-03-14",
      "count": 4433
    },
    {
      "date": "2026-03-13",
      "count": 4360
    },
    {
      "date": "2026-03-12",
      "count": 4580
    },
    {
      "date": "2026-03-11",
      "count": 4776
    },
    {
      "date": "2026-03-10",
      "count": 4558
    },
    {
      "date": "2026-03-09",
      "count": 4327
    },
    {
      "date": "2026-03-08",
      "count": 4579
    },
    {
      "date": "2026-03-07",
      "count": 6659
    },
    {
      "date": "2026-03-06",
      "count": 6501
    },
    {
      "date": "2026-03-05",
      "count": 6304
    },
    {
      "date": "2026-03-04",
      "count": 5961
    },
    {
      "date": "2026-03-03",
      "count": 4897
    },
    {
      "date": "2026-03-02",
      "count": 3020
    },
    {
      "date": "2026-03-01",
      "count": 6760
    },
    {
      "date": "2026-02-28",
      "count": 6730
    },
    {
      "date": "2026-02-27",
      "count": 6408
    },
    {
      "date": "2026-02-26",
      "count": 6161
    },
    {
      "date": "2026-02-25",
      "count": 6542
    },
    {
      "date": "2026-02-24",
      "count": 6522
    },
    {
      "date": "2026-02-23",
      "count": 6471
    },
    {
      "date": "2026-02-22",
      "count": 7229
    },
    {
      "date": "2026-02-21",
      "count": 7450
    },
    {
      "date": "2026-02-20",
      "count": 6983
    },
    {
      "date": "2026-02-19",
      "count": 7078
    }
  ]
}