{
  "total": 169370,
  "last24h": 7919,
  "recentTxs": [
    {
      "hash": "0x0a64d945920582f69a5396f4ff59b360839444dee807274b76f2f79bd02ede01",
      "from": "0x4289516D5a5Dc4D7BF044b8cfA8010f87f469819",
      "value": "0",
      "blockNumber": 39694172,
      "timeStamp": 1774126180
    },
    {
      "hash": "0xf8f47615653240d39c9e8c2e25356514b288a9ec4ead0c7c4f5af5acb98944da",
      "from": "0x4289516D5a5Dc4D7BF044b8cfA8010f87f469819",
      "value": "0",
      "blockNumber": 39694168,
      "timeStamp": 1774126174
    },
    {
      "hash": "0x53ce2df471fbdfb0ee7e07f617fd97ddbbea452fbbe2fa37f4ab045cdeafb8ec",
      "from": "0x0979bf454096Dd5F6864f3825dE0a5D4e8625dBF",
      "value": "0",
      "blockNumber": 39694159,
      "timeStamp": 1774126148
    },
    {
      "hash": "0x160007b6c2f27be7d6dee5aecc2d8e726ebd320975833b71bbc6a7afcadcaca4",
      "from": "0xE17BeCE8137f74Cf9784e82B96381430D5520BA8",
      "value": "0",
      "blockNumber": 39694147,
      "timeStamp": 1774126127
    },
    {
      "hash": "0xbc36e40725619cac45458083830c9db97252c1a7acb2491321f0d5ededd48f04",
      "from": "0xE86E709e002a5cbAFc895375f553d7eAFA2abE0a",
      "value": "0",
      "blockNumber": 39694137,
      "timeStamp": 1774126109
    },
    {
      "hash": "0x5104cfcc4d5dabc3f51f387926392ea275eb20e3399f57fef328fb9aa1aed051",
      "from": "0xeab58DA06e1e9C7F61F8942840c8dd7f4e2f4F0C",
      "value": "0",
      "blockNumber": 39694120,
      "timeStamp": 1774126074
    },
    {
      "hash": "0x90a27fce1ba8e9b254a1f1f376c74ca5bd7302dbd52a587bcc8381ed965a57ee",
      "from": "0xeab58DA06e1e9C7F61F8942840c8dd7f4e2f4F0C",
      "value": "0",
      "blockNumber": 39694116,
      "timeStamp": 1774126068
    },
    {
      "hash": "0xf7b63fccc803e8630943ccdc5504dc95ea3d41922c82ef339a4e89f51b0fe383",
      "from": "0x9e795e3255C9449743b22Daf4166107714Fc9Ee8",
      "value": "0",
      "blockNumber": 39694108,
      "timeStamp": 1774126050
    },
    {
      "hash": "0xfbbabee885f537f9c48d483d216dce5665eddbc53f4b1a81474abac0c1c7b26b",
      "from": "0x532Ef0a2CD550b2F9b9D35c33A5dF2922F4aDcAe",
      "value": "0",
      "blockNumber": 39694099,
      "timeStamp": 1774126025
    },
    {
      "hash": "0xa71b5229b61ea21b931a492c18356d2a6848db876f275ae64638313b6ea86f99",
      "from": "0x476888b2fCdc1c30A8Ba79Bdfbe655576d860f32",
      "value": "0",
      "blockNumber": 39694089,
      "timeStamp": 1774126007
    }
  ],
  "lastUpdated": "2026-03-21T20:50:43.147Z",
  "dailyCounts": [
    {
      "date": "2026-03-21",
      "count": 3745
    },
    {
      "date": "2026-03-20",
      "count": 4174
    },
    {
      "date": "2026-03-19",
      "count": 4182
    },
    {
      "date": "2026-03-18",
      "count": 4434
    },
    {
      "date": "2026-03-17",
      "count": 4407
    },
    {
      "date": "2026-03-16",
      "count": 4276
    },
    {
      "date": "2026-03-15",
      "count": 4437
    },
    {
      "date": "2026-03-14",
      "count": 4433
    },
    {
      "date": "2026-03-13",
      "count": 4360
    },
    {
      "date": "2026-03-12",
      "count": 4580
    },
    {
      "date": "2026-03-11",
      "count": 4776
    },
    {
      "date": "2026-03-10",
      "count": 4558
    },
    {
      "date": "2026-03-09",
      "count": 4327
    },
    {
      "date": "2026-03-08",
      "count": 4579
    },
    {
      "date": "2026-03-07",
      "count": 6659
    },
    {
      "date": "2026-03-06",
      "count": 6501
    },
    {
      "date": "2026-03-05",
      "count": 6304
    },
    {
      "date": "2026-03-04",
      "count": 5961
    },
    {
      "date": "2026-03-03",
      "count": 4897
    },
    {
      "date": "2026-03-02",
      "count": 3020
    },
    {
      "date": "2026-03-01",
      "count": 6760
    },
    {
      "date": "2026-02-28",
      "count": 6730
    },
    {
      "date": "2026-02-27",
      "count": 6408
    },
    {
      "date": "2026-02-26",
      "count": 6161
    },
    {
      "date": "2026-02-25",
      "count": 6542
    },
    {
      "date": "2026-02-24",
      "count": 6522
    },
    {
      "date": "2026-02-23",
      "count": 6471
    },
    {
      "date": "2026-02-22",
      "count": 7229
    },
    {
      "date": "2026-02-21",
      "count": 7450
    },
    {
      "date": "2026-02-20",
      "count": 6983
    }
  ]
}