{
  "total": 265165,
  "last24h": 7550,
  "recentTxs": [
    {
      "hash": "0xadc047c909fa3cf56e19d88f5b06e3734c2bf361d336a7d9a559b2ab41c0ed5f",
      "from": "0xfD8A588102a25412ECa01b95d44502DEff743896",
      "value": "0",
      "blockNumber": 40634640,
      "timeStamp": 1775822966
    },
    {
      "hash": "0xcce121aa3ede715200cdc895e401492c1efbfff36f16d2d3da397a485a9cbee3",
      "from": "0x04DDa8C15ea68339e23BEF582048A667DC073Be4",
      "value": "0",
      "blockNumber": 40634630,
      "timeStamp": 1775822950
    },
    {
      "hash": "0xe983a48a2a38ea6bb0edb0218bdd86b2f7ffdb63b14522b77fd06e5a751f3b2c",
      "from": "0x8025be82a535E348A283543D0fe001037a7d6e1E",
      "value": "0",
      "blockNumber": 40634622,
      "timeStamp": 1775822935
    },
    {
      "hash": "0xdda8465268844311b10e349d8739daa5b71dfb14b835341d11c8c2c160f6745c",
      "from": "0x93d61da2Af503bc082f699d6Fd7b4D7df91cE8A5",
      "value": "0",
      "blockNumber": 40634606,
      "timeStamp": 1775822906
    },
    {
      "hash": "0x89f6760385e2a01fb7d7cbc9c44e92197ff2a394e0dab8a54dc1b46d1fd6f6b3",
      "from": "0x93d61da2Af503bc082f699d6Fd7b4D7df91cE8A5",
      "value": "0",
      "blockNumber": 40634603,
      "timeStamp": 1775822901
    },
    {
      "hash": "0xecf6faac7717ebcea1cea59ebf4d9769a29add59a6c3734b3dec8d887de4f7c8",
      "from": "0xD19F1FB4a466c55C09DfEe2bC08622A83c373A25",
      "value": "0",
      "blockNumber": 40634593,
      "timeStamp": 1775822886
    },
    {
      "hash": "0x5055d3adb288bff0a589122a5e1be40216a71a10d5cf2d8b6397f1d2c987fe2d",
      "from": "0xde7b9d559C9C27A483Ab3f9B6B4de865a44D84d7",
      "value": "0",
      "blockNumber": 40634585,
      "timeStamp": 1775822871
    },
    {
      "hash": "0x23c4dc4d9b63f0b162b04fd6ca1d02e18d4f64dac297bdb22a610e09bb0820f2",
      "from": "0x43F61252a26BbF9eB418422c012a3a34883d019E",
      "value": "0",
      "blockNumber": 40634575,
      "timeStamp": 1775822855
    },
    {
      "hash": "0x2c968af127ff785ec26e634185e00f539b64db98025ae138d6a9d37c26e3ff84",
      "from": "0xa77e650bD4c4800113b1B811f840d44d25F59cAb",
      "value": "0",
      "blockNumber": 40634556,
      "timeStamp": 1775822825
    },
    {
      "hash": "0x2467ba1d4e2d2995de5c71fb9b2f409fdbaf27ca7b63c34c167f815190461eff",
      "from": "0xa77e650bD4c4800113b1B811f840d44d25F59cAb",
      "value": "0",
      "blockNumber": 40634552,
      "timeStamp": 1775822816
    }
  ],
  "lastUpdated": "2026-04-10T12:09:54.241Z",
  "dailyCounts": [
    {
      "date": "2026-04-10",
      "count": 2462
    },
    {
      "date": "2026-04-09",
      "count": 5088
    },
    {
      "date": "2026-04-08",
      "count": 4965
    },
    {
      "date": "2026-04-07",
      "count": 4988
    },
    {
      "date": "2026-04-06",
      "count": 5104
    },
    {
      "date": "2026-04-05",
      "count": 5356
    },
    {
      "date": "2026-04-04",
      "count": 5300
    },
    {
      "date": "2026-04-03",
      "count": 5324
    },
    {
      "date": "2026-04-02",
      "count": 5185
    },
    {
      "date": "2026-04-01",
      "count": 5215
    },
    {
      "date": "2026-03-31",
      "count": 5120
    },
    {
      "date": "2026-03-30",
      "count": 4753
    },
    {
      "date": "2026-03-29",
      "count": 4977
    },
    {
      "date": "2026-03-28",
      "count": 4773
    },
    {
      "date": "2026-03-27",
      "count": 4763
    },
    {
      "date": "2026-03-26",
      "count": 4312
    },
    {
      "date": "2026-03-25",
      "count": 4521
    },
    {
      "date": "2026-03-24",
      "count": 4326
    },
    {
      "date": "2026-03-23",
      "count": 4480
    },
    {
      "date": "2026-03-22",
      "count": 4246
    },
    {
      "date": "2026-03-21",
      "count": 4282
    },
    {
      "date": "2026-03-20",
      "count": 4174
    },
    {
      "date": "2026-03-19",
      "count": 4182
    },
    {
      "date": "2026-03-18",
      "count": 4434
    },
    {
      "date": "2026-03-17",
      "count": 4407
    },
    {
      "date": "2026-03-16",
      "count": 4276
    },
    {
      "date": "2026-03-15",
      "count": 4437
    },
    {
      "date": "2026-03-14",
      "count": 4433
    },
    {
      "date": "2026-03-13",
      "count": 4360
    },
    {
      "date": "2026-03-12",
      "count": 4580
    }
  ]
}