{
  "total": 269325,
  "last24h": 6622,
  "recentTxs": [
    {
      "hash": "0x4e14c3ecc29530f2d8deaae05a489fe7127489f9ceb0eec6bf0a1ffa436ccd4f",
      "from": "0x3E6f6854925E4887441E95dFbF1fF856F0793a94",
      "value": "0",
      "blockNumber": 40672778,
      "timeStamp": 1775892905
    },
    {
      "hash": "0x526490ff9aaeffbd7abb219d870b4916d0e309ea37c9ccdc49db46500cc0343c",
      "from": "0x2800925ce678aCa2e14C12778D9890Fb6b22cfF8",
      "value": "0",
      "blockNumber": 40672771,
      "timeStamp": 1775892890
    },
    {
      "hash": "0x5cfece41815962296cda92ad8f03d2082739a7e00b099fcc2d0b34e93de59a0a",
      "from": "0xE2B995a0EF37b6a4ed097583e273Ee3E41A99ab3",
      "value": "0",
      "blockNumber": 40672761,
      "timeStamp": 1775892874
    },
    {
      "hash": "0xf34e17a078fbfb6e438ce919d6eefeca64fb87ba7a2492a820d95400284d04e0",
      "from": "0x52E90577baE1A628C3B101c9d557135aE7041d51",
      "value": "0",
      "blockNumber": 40672746,
      "timeStamp": 1775892850
    },
    {
      "hash": "0x9243e4ae5312f893f233d87ad2fbd4e1808c5ac40083de721ab7d77e0ced74f6",
      "from": "0x52E90577baE1A628C3B101c9d557135aE7041d51",
      "value": "0",
      "blockNumber": 40672742,
      "timeStamp": 1775892843
    },
    {
      "hash": "0xcb5e9142b12c1dedb05157f25145eae26d36f5ccd9dab855fe8d53e7260690a2",
      "from": "0xe357de850F8101034e88924A80a7fedF22A77530",
      "value": "0",
      "blockNumber": 40672733,
      "timeStamp": 1775892828
    },
    {
      "hash": "0x9feaec2dc540011a8202fceaeff2fbd6a854482bd888fe915d9adc52097441da",
      "from": "0x78837bCCE57c5E33E7E99Fb90311957A072E6deA",
      "value": "0",
      "blockNumber": 40672724,
      "timeStamp": 1775892814
    },
    {
      "hash": "0xd5b320b953e804907a3621e9d406171c9f84db9a14bcc7d55bb83a1dad258284",
      "from": "0x49C95aF01506bDdb6F78198d69f614d126e615A4",
      "value": "0",
      "blockNumber": 40672715,
      "timeStamp": 1775892797
    },
    {
      "hash": "0x7da43bb9f7e1878e41619d340e2e98c037f6a30cc25dd27daec64d17847d29eb",
      "from": "0x053DDdc44B67880E7301322eD3c082B3f6aC57bF",
      "value": "0",
      "blockNumber": 40672702,
      "timeStamp": 1775892772
    },
    {
      "hash": "0xa8a1aad5db69e4f84de8fd94f8d1d9b84c185a5462756b2cce684b24bc2931f2",
      "from": "0x053DDdc44B67880E7301322eD3c082B3f6aC57bF",
      "value": "0",
      "blockNumber": 40672698,
      "timeStamp": 1775892766
    }
  ],
  "lastUpdated": "2026-04-11T07:36:02.720Z",
  "dailyCounts": [
    {
      "date": "2026-04-11",
      "count": 1584
    },
    {
      "date": "2026-04-10",
      "count": 5038
    },
    {
      "date": "2026-04-09",
      "count": 5088
    },
    {
      "date": "2026-04-08",
      "count": 4965
    },
    {
      "date": "2026-04-07",
      "count": 4988
    },
    {
      "date": "2026-04-06",
      "count": 5104
    },
    {
      "date": "2026-04-05",
      "count": 5356
    },
    {
      "date": "2026-04-04",
      "count": 5300
    },
    {
      "date": "2026-04-03",
      "count": 5324
    },
    {
      "date": "2026-04-02",
      "count": 5185
    },
    {
      "date": "2026-04-01",
      "count": 5215
    },
    {
      "date": "2026-03-31",
      "count": 5120
    },
    {
      "date": "2026-03-30",
      "count": 4753
    },
    {
      "date": "2026-03-29",
      "count": 4977
    },
    {
      "date": "2026-03-28",
      "count": 4773
    },
    {
      "date": "2026-03-27",
      "count": 4763
    },
    {
      "date": "2026-03-26",
      "count": 4312
    },
    {
      "date": "2026-03-25",
      "count": 4521
    },
    {
      "date": "2026-03-24",
      "count": 4326
    },
    {
      "date": "2026-03-23",
      "count": 4480
    },
    {
      "date": "2026-03-22",
      "count": 4246
    },
    {
      "date": "2026-03-21",
      "count": 4282
    },
    {
      "date": "2026-03-20",
      "count": 4174
    },
    {
      "date": "2026-03-19",
      "count": 4182
    },
    {
      "date": "2026-03-18",
      "count": 4434
    },
    {
      "date": "2026-03-17",
      "count": 4407
    },
    {
      "date": "2026-03-16",
      "count": 4276
    },
    {
      "date": "2026-03-15",
      "count": 4437
    },
    {
      "date": "2026-03-14",
      "count": 4433
    },
    {
      "date": "2026-03-13",
      "count": 4360
    }
  ]
}