{
  "total": 176260,
  "last24h": 6353,
  "recentTxs": [
    {
      "hash": "0xa418687739870483c0b785b2e394e3fd0074a6a8fc4c1c71c518dbd6e828ecf8",
      "from": "0x2798d1bA2Ab56730Aa418Ced85503fb71f3296fE",
      "value": "0",
      "blockNumber": 39771282,
      "timeStamp": 1774266303
    },
    {
      "hash": "0xe0d297029a5b55eae097e422ed237f28c1237fa9c1133b339041624688d7b548",
      "from": "0x2798d1bA2Ab56730Aa418Ced85503fb71f3296fE",
      "value": "0",
      "blockNumber": 39771278,
      "timeStamp": 1774266295
    },
    {
      "hash": "0x9fd67ec3d52b42405b78c49fc691975c048aeb611188e118a5d86c808aa56dca",
      "from": "0xD37f34164671e7D59CB730245E8233522D0Ed945",
      "value": "0",
      "blockNumber": 39771268,
      "timeStamp": 1774266277
    },
    {
      "hash": "0x65ec227a481fe596b62719e298d1cc75bc57578812827237a1b86ae3befa308a",
      "from": "0x0A505574Af625b0D7284ED5c56D96129f3db5701",
      "value": "0",
      "blockNumber": 39771256,
      "timeStamp": 1774266259
    },
    {
      "hash": "0xc5c3e8cef63afe374abaa006be2966bd892eff2d002cb80d03bdc68c5dde59b5",
      "from": "0xFd043C2b2Ded460C09949bd68bE53E76f921d388",
      "value": "0",
      "blockNumber": 39771243,
      "timeStamp": 1774266239
    },
    {
      "hash": "0x088e5e1e393de03af6a8affd29808c72a87e215c1d26b37a2edacde7a14647fa",
      "from": "0x44CeAd7C490a043d6c24CcA3DAeB7a88d55cFB0c",
      "value": "0",
      "blockNumber": 39771207,
      "timeStamp": 1774266172
    },
    {
      "hash": "0x6c23935fb7945bbca958c7f9bb40045705002e59736633591242c3adaa66aeb4",
      "from": "0x44CeAd7C490a043d6c24CcA3DAeB7a88d55cFB0c",
      "value": "0",
      "blockNumber": 39771203,
      "timeStamp": 1774266165
    },
    {
      "hash": "0x0aa933e9eaa164a2a55566dc0ea4dd0be4c4b7b9a5227cc69e8a6fd1855254a0",
      "from": "0xE6c17e0497E0C466D4Db098423E1a48FaAB74b6F",
      "value": "0",
      "blockNumber": 39771193,
      "timeStamp": 1774266147
    },
    {
      "hash": "0x7762f8f84fd52a6885a5c13ad61816619fab57786c533a802915e302b7964fe9",
      "from": "0x253437475c99f9D6D8A29385736D807401F4F531",
      "value": "0",
      "blockNumber": 39771183,
      "timeStamp": 1774266128
    },
    {
      "hash": "0xd47c22617d830dd1333da8ba9e6e237784f8b88ab8d5b243cc46270309147cbb",
      "from": "0xF586468F5378Dd08C49b9B75bc90476947C0a08b",
      "value": "0",
      "blockNumber": 39771171,
      "timeStamp": 1774266110
    }
  ],
  "lastUpdated": "2026-03-23T11:46:20.005Z",
  "dailyCounts": [
    {
      "date": "2026-03-23",
      "count": 2107
    },
    {
      "date": "2026-03-22",
      "count": 4246
    },
    {
      "date": "2026-03-21",
      "count": 4282
    },
    {
      "date": "2026-03-20",
      "count": 4174
    },
    {
      "date": "2026-03-19",
      "count": 4182
    },
    {
      "date": "2026-03-18",
      "count": 4434
    },
    {
      "date": "2026-03-17",
      "count": 4407
    },
    {
      "date": "2026-03-16",
      "count": 4276
    },
    {
      "date": "2026-03-15",
      "count": 4437
    },
    {
      "date": "2026-03-14",
      "count": 4433
    },
    {
      "date": "2026-03-13",
      "count": 4360
    },
    {
      "date": "2026-03-12",
      "count": 4580
    },
    {
      "date": "2026-03-11",
      "count": 4776
    },
    {
      "date": "2026-03-10",
      "count": 4558
    },
    {
      "date": "2026-03-09",
      "count": 4327
    },
    {
      "date": "2026-03-08",
      "count": 4579
    },
    {
      "date": "2026-03-07",
      "count": 6659
    },
    {
      "date": "2026-03-06",
      "count": 6501
    },
    {
      "date": "2026-03-05",
      "count": 6304
    },
    {
      "date": "2026-03-04",
      "count": 5961
    },
    {
      "date": "2026-03-03",
      "count": 4897
    },
    {
      "date": "2026-03-02",
      "count": 3020
    },
    {
      "date": "2026-03-01",
      "count": 6760
    },
    {
      "date": "2026-02-28",
      "count": 6730
    },
    {
      "date": "2026-02-27",
      "count": 6408
    },
    {
      "date": "2026-02-26",
      "count": 6161
    },
    {
      "date": "2026-02-25",
      "count": 6542
    },
    {
      "date": "2026-02-24",
      "count": 6522
    },
    {
      "date": "2026-02-23",
      "count": 6471
    },
    {
      "date": "2026-02-22",
      "count": 7229
    }
  ]
}