{
  "total": 273180,
  "last24h": 5439,
  "recentTxs": [
    {
      "hash": "0xe0576f9524450bc563751269b078fad8b7abf9076b0e3f46e9cc6461bbc42e71",
      "from": "0x089FDAa66019476922CF08aBF67e1a414a73eD37",
      "value": "0",
      "blockNumber": 40707854,
      "timeStamp": 1775955676
    },
    {
      "hash": "0x5d84c7a82e58bb96ff7c8ef94778692ce0a0bf1ea58c2261087a5e9b603cb9ba",
      "from": "0x4728B40dC6B20b60ad3f11ACc78345e4ca6682e6",
      "value": "0",
      "blockNumber": 40707841,
      "timeStamp": 1775955650
    },
    {
      "hash": "0x14b7daaa2f14d20d8d474cf4b54e24380477c4c669825a577874e073dff6d468",
      "from": "0x00D49f88E1560fF06BB9392e81D65C433eebE2d7",
      "value": "0",
      "blockNumber": 40707833,
      "timeStamp": 1775955635
    },
    {
      "hash": "0x5d27406142d580563f1fd037a9da12dc05a4334dffcb1932d182a0664c89554b",
      "from": "0xcd1d33DadFd31eBe78de43F0320DbF2df8E3F33C",
      "value": "0",
      "blockNumber": 40707816,
      "timeStamp": 1775955595
    },
    {
      "hash": "0xcf0505cbcc3086af0dc467e3c3d63331e65cf657e33cc63ccf1e93d97de55566",
      "from": "0xcd1d33DadFd31eBe78de43F0320DbF2df8E3F33C",
      "value": "0",
      "blockNumber": 40707812,
      "timeStamp": 1775955589
    },
    {
      "hash": "0x93278a3cf946e45169eea0e149fc9f3010f172d34cddd7b07ebb090ed7fbbe69",
      "from": "0x863f6f1D923A4d3b6F64596f58c13b0f4e50cBfd",
      "value": "0",
      "blockNumber": 40707804,
      "timeStamp": 1775955574
    },
    {
      "hash": "0xcd339f28eb5fda18835282e5d993429b6bed8bff732c5b460261e4cc4cf6765a",
      "from": "0x9F9E3FF7B89B9eB32F4d226c2c02b01C16f49B5e",
      "value": "0",
      "blockNumber": 40707794,
      "timeStamp": 1775955556
    },
    {
      "hash": "0xb7e2df05dfe56961b3b72cdb28a024227515400b4b202ec1cd5fdd32e77f3b14",
      "from": "0x19179EB4910070a6AFFe298A2cb29a194F7C6E7E",
      "value": "0",
      "blockNumber": 40707787,
      "timeStamp": 1775955541
    },
    {
      "hash": "0x281c7fcd210ea4e980f756f68978c67b07e72a890b71618bdf39a1da4fe02e18",
      "from": "0x210Fd7F40Dc6b28dD5e7Fa1cB9382599A23BD81c",
      "value": "0",
      "blockNumber": 40707773,
      "timeStamp": 1775955515
    },
    {
      "hash": "0x098b6ce79d2bba3e8d2f993458f9ffa6c70cb15f2f3aa3ffb37338d82ad00fe4",
      "from": "0x210Fd7F40Dc6b28dD5e7Fa1cB9382599A23BD81c",
      "value": "0",
      "blockNumber": 40707770,
      "timeStamp": 1775955510
    }
  ],
  "lastUpdated": "2026-04-12T01:03:31.261Z",
  "dailyCounts": [
    {
      "date": "2026-04-12",
      "count": 241
    },
    {
      "date": "2026-04-11",
      "count": 5198
    },
    {
      "date": "2026-04-10",
      "count": 5038
    },
    {
      "date": "2026-04-09",
      "count": 5088
    },
    {
      "date": "2026-04-08",
      "count": 4965
    },
    {
      "date": "2026-04-07",
      "count": 4988
    },
    {
      "date": "2026-04-06",
      "count": 5104
    },
    {
      "date": "2026-04-05",
      "count": 5356
    },
    {
      "date": "2026-04-04",
      "count": 5300
    },
    {
      "date": "2026-04-03",
      "count": 5324
    },
    {
      "date": "2026-04-02",
      "count": 5185
    },
    {
      "date": "2026-04-01",
      "count": 5215
    },
    {
      "date": "2026-03-31",
      "count": 5120
    },
    {
      "date": "2026-03-30",
      "count": 4753
    },
    {
      "date": "2026-03-29",
      "count": 4977
    },
    {
      "date": "2026-03-28",
      "count": 4773
    },
    {
      "date": "2026-03-27",
      "count": 4763
    },
    {
      "date": "2026-03-26",
      "count": 4312
    },
    {
      "date": "2026-03-25",
      "count": 4521
    },
    {
      "date": "2026-03-24",
      "count": 4326
    },
    {
      "date": "2026-03-23",
      "count": 4480
    },
    {
      "date": "2026-03-22",
      "count": 4246
    },
    {
      "date": "2026-03-21",
      "count": 4282
    },
    {
      "date": "2026-03-20",
      "count": 4174
    },
    {
      "date": "2026-03-19",
      "count": 4182
    },
    {
      "date": "2026-03-18",
      "count": 4434
    },
    {
      "date": "2026-03-17",
      "count": 4407
    },
    {
      "date": "2026-03-16",
      "count": 4276
    },
    {
      "date": "2026-03-15",
      "count": 4437
    },
    {
      "date": "2026-03-14",
      "count": 4433
    }
  ]
}