{
  "total": 205942,
  "last24h": 9387,
  "recentTxs": [
    {
      "hash": "0x69e5e0df6c0ece8f464a322fa722f859190bc948336ed4d380a73615171b96d4",
      "from": "0xE3762601aE3813339C1b167D838C2e70fA7E2A2E",
      "value": "0",
      "blockNumber": 40077239,
      "timeStamp": 1774822361
    },
    {
      "hash": "0xc68c372e539260703cdbc983ad1141aa6d8f9936d918f618a560bfa0c53e3b19",
      "from": "0xDFa2c99e48DeC78531D3EB2cD9c7f3C4660511d0",
      "value": "0",
      "blockNumber": 40077231,
      "timeStamp": 1774822347
    },
    {
      "hash": "0x4412006f33c0ed80fbd3798492407bcbcc306903f05b108723c888f67282126b",
      "from": "0x1d3B965d7FbA66768484Ba28284B5D0E6f2e6428",
      "value": "0",
      "blockNumber": 40077223,
      "timeStamp": 1774822331
    },
    {
      "hash": "0x25b0a345f79947a411cf0dfbe10ed8bf29521e6aa36bc510b25f1a62e933f10c",
      "from": "0x934b8ECE9E61550b97B624D21f0848427Ffa7A23",
      "value": "0",
      "blockNumber": 40077206,
      "timeStamp": 1774822301
    },
    {
      "hash": "0x99330987d991dd30824ceca0cecb0e61a6b3923745bfcb61449cad7a3b99004c",
      "from": "0x934b8ECE9E61550b97B624D21f0848427Ffa7A23",
      "value": "0",
      "blockNumber": 40077204,
      "timeStamp": 1774822296
    },
    {
      "hash": "0x009b6698c3598af15e891b82ddc6fa7b026ab5b6bdbd22c23c7ce2beac417b4c",
      "from": "0x8cbA81AcC14758461a8a9BA46529e939693695bB",
      "value": "0",
      "blockNumber": 40077195,
      "timeStamp": 1774822277
    },
    {
      "hash": "0x66ac94cfc601f1f5aa88418163a72c5f2fac05957035ea3b0131c4af7adf6922",
      "from": "0x8Daced862A0ef5a0f7f06353dB7cF0A811c9F174",
      "value": "0",
      "blockNumber": 40077189,
      "timeStamp": 1774822264
    },
    {
      "hash": "0x71b9dcaf47534fc953cea1f612fadc04f1125d555fca7dc8bb431bff6a8ae081",
      "from": "0x92188d47c26CA00F3208f065a11426A799ef6A72",
      "value": "0",
      "blockNumber": 40077181,
      "timeStamp": 1774822248
    },
    {
      "hash": "0x9fda703617e0aa03e076f9e1ac87fc6431a8f11544122e8bade50068233fecee",
      "from": "0xC86Ae87A54C8f5696D798fd86deE73d0a4A39965",
      "value": "0",
      "blockNumber": 40077168,
      "timeStamp": 1774822220
    },
    {
      "hash": "0x3a6e53b19486c306794f51937adc3d6cb58823509324ef22d09189f36967fdf3",
      "from": "0xC86Ae87A54C8f5696D798fd86deE73d0a4A39965",
      "value": "0",
      "blockNumber": 40077163,
      "timeStamp": 1774822212
    }
  ],
  "lastUpdated": "2026-03-29T22:13:16.350Z",
  "dailyCounts": [
    {
      "date": "2026-03-29",
      "count": 4614
    },
    {
      "date": "2026-03-28",
      "count": 4773
    },
    {
      "date": "2026-03-27",
      "count": 4763
    },
    {
      "date": "2026-03-26",
      "count": 4312
    },
    {
      "date": "2026-03-25",
      "count": 4521
    },
    {
      "date": "2026-03-24",
      "count": 4326
    },
    {
      "date": "2026-03-23",
      "count": 4480
    },
    {
      "date": "2026-03-22",
      "count": 4246
    },
    {
      "date": "2026-03-21",
      "count": 4282
    },
    {
      "date": "2026-03-20",
      "count": 4174
    },
    {
      "date": "2026-03-19",
      "count": 4182
    },
    {
      "date": "2026-03-18",
      "count": 4434
    },
    {
      "date": "2026-03-17",
      "count": 4407
    },
    {
      "date": "2026-03-16",
      "count": 4276
    },
    {
      "date": "2026-03-15",
      "count": 4437
    },
    {
      "date": "2026-03-14",
      "count": 4433
    },
    {
      "date": "2026-03-13",
      "count": 4360
    },
    {
      "date": "2026-03-12",
      "count": 4580
    },
    {
      "date": "2026-03-11",
      "count": 4776
    },
    {
      "date": "2026-03-10",
      "count": 4558
    },
    {
      "date": "2026-03-09",
      "count": 4327
    },
    {
      "date": "2026-03-08",
      "count": 4579
    },
    {
      "date": "2026-03-07",
      "count": 6659
    },
    {
      "date": "2026-03-06",
      "count": 6501
    },
    {
      "date": "2026-03-05",
      "count": 6304
    },
    {
      "date": "2026-03-04",
      "count": 5961
    },
    {
      "date": "2026-03-03",
      "count": 4897
    },
    {
      "date": "2026-03-02",
      "count": 3020
    },
    {
      "date": "2026-03-01",
      "count": 6760
    },
    {
      "date": "2026-02-28",
      "count": 6730
    }
  ]
}