{
  "total": 291480,
  "last24h": 8388,
  "recentTxs": [
    {
      "hash": "0x53b3241b0855b637a747d9364ed2853ab6a1732b036e85060bd42b94f2285d7d",
      "from": "0x7E099C71aA46f914CCe7063e2f8127258b1AFfc4",
      "value": "0",
      "blockNumber": 40884111,
      "timeStamp": 1776278238
    },
    {
      "hash": "0x36ab1cc4d68b7e61399e2f4e6554c77ab33990be9ca75f2702ab590c41ca261c",
      "from": "0x6736DDDca7cc55f01fb3E038588efF86196B2860",
      "value": "0",
      "blockNumber": 40884091,
      "timeStamp": 1776278198
    },
    {
      "hash": "0xa95ee7a94f349968f1ef884003a2e94215bb659c2272b5b77c7dd86edf20f42d",
      "from": "0x6736DDDca7cc55f01fb3E038588efF86196B2860",
      "value": "0",
      "blockNumber": 40884089,
      "timeStamp": 1776278192
    },
    {
      "hash": "0xfdc76165015f08f449ec2bfef1d7fa9029e86aae738cefe6476d50c1c52e94a4",
      "from": "0x439D3b8075B6028cBD455380DFA5b933d5E97AE8",
      "value": "0",
      "blockNumber": 40884075,
      "timeStamp": 1776278169
    },
    {
      "hash": "0x10515737f8c5fcf573890dd37ec6f98c8fed26c3561681e3ab360bb65f03da14",
      "from": "0xbbB6AA65B994800F70D5cf88Af0d8b8C51381402",
      "value": "0",
      "blockNumber": 40884063,
      "timeStamp": 1776278148
    },
    {
      "hash": "0x100a49693a469b82125d760c362a2ca341bfabe86a6065c386644f73d67b379b",
      "from": "0x4E405a882EE9b796807d4aC6650F05ebEe89Fe08",
      "value": "0",
      "blockNumber": 40884053,
      "timeStamp": 1776278123
    },
    {
      "hash": "0xee0d7506fa659e344c09bf98055345cbb14480f14d802394effd9b7680a6bcb9",
      "from": "0xEb909D2F80b87a920Dc738E84F1A2C07ab5Db9F8",
      "value": "0",
      "blockNumber": 40884031,
      "timeStamp": 1776278084
    },
    {
      "hash": "0xe9fb90917540ebf9dc41887084cc7512053254673a129559ca380ac98ddbb798",
      "from": "0xEb909D2F80b87a920Dc738E84F1A2C07ab5Db9F8",
      "value": "0",
      "blockNumber": 40884027,
      "timeStamp": 1776278075
    },
    {
      "hash": "0xd5b551e2d85fa4340de4222ba6cfef02e4f89b5ce28aa915db38f2e9fbd3939f",
      "from": "0x9B9035631BC0Cb00c7B50e0d77B05FeA319591ef",
      "value": "0",
      "blockNumber": 40884016,
      "timeStamp": 1776278056
    },
    {
      "hash": "0x98950940d215bd48b1c364deccfcc4691781ada140f71171c708fb875bda36f4",
      "from": "0xff13B3d07329965801935147a20dbe6b3F1A93a8",
      "value": "0",
      "blockNumber": 40884006,
      "timeStamp": 1776278036
    }
  ],
  "lastUpdated": "2026-04-15T18:37:49.644Z",
  "dailyCounts": [
    {
      "date": "2026-04-15",
      "count": 3497
    },
    {
      "date": "2026-04-14",
      "count": 4891
    },
    {
      "date": "2026-04-13",
      "count": 4983
    },
    {
      "date": "2026-04-12",
      "count": 5170
    },
    {
      "date": "2026-04-11",
      "count": 5198
    },
    {
      "date": "2026-04-10",
      "count": 5038
    },
    {
      "date": "2026-04-09",
      "count": 5088
    },
    {
      "date": "2026-04-08",
      "count": 4965
    },
    {
      "date": "2026-04-07",
      "count": 4988
    },
    {
      "date": "2026-04-06",
      "count": 5104
    },
    {
      "date": "2026-04-05",
      "count": 5356
    },
    {
      "date": "2026-04-04",
      "count": 5300
    },
    {
      "date": "2026-04-03",
      "count": 5324
    },
    {
      "date": "2026-04-02",
      "count": 5185
    },
    {
      "date": "2026-04-01",
      "count": 5215
    },
    {
      "date": "2026-03-31",
      "count": 5120
    },
    {
      "date": "2026-03-30",
      "count": 4753
    },
    {
      "date": "2026-03-29",
      "count": 4977
    },
    {
      "date": "2026-03-28",
      "count": 4773
    },
    {
      "date": "2026-03-27",
      "count": 4763
    },
    {
      "date": "2026-03-26",
      "count": 4312
    },
    {
      "date": "2026-03-25",
      "count": 4521
    },
    {
      "date": "2026-03-24",
      "count": 4326
    },
    {
      "date": "2026-03-23",
      "count": 4480
    },
    {
      "date": "2026-03-22",
      "count": 4246
    },
    {
      "date": "2026-03-21",
      "count": 4282
    },
    {
      "date": "2026-03-20",
      "count": 4174
    },
    {
      "date": "2026-03-19",
      "count": 4182
    },
    {
      "date": "2026-03-18",
      "count": 4434
    },
    {
      "date": "2026-03-17",
      "count": 4407
    }
  ]
}