{
  "total": 154874,
  "last24h": 5561,
  "recentTxs": [
    {
      "hash": "0xfdbad00e4ee65857b1a1ea03f877500d8d9dfc26802c03ed8699210cb9a24a55",
      "from": "0xdA22293aa75E005f7A6411a85f5aE053eBAfd3a9",
      "value": "0",
      "blockNumber": 40933209,
      "timeStamp": 1776368955
    },
    {
      "hash": "0x67ca32c6027bd6d623fd451db38a9ac0622ded4f2950d31f28cd9cd7ea455cf2",
      "from": "0xdA22293aa75E005f7A6411a85f5aE053eBAfd3a9",
      "value": "0",
      "blockNumber": 40933203,
      "timeStamp": 1776368944
    },
    {
      "hash": "0x83543dce2d20e5edaae715f27d3e9d8408fb2a2ece080b46ebda7b09c5bb7feb",
      "from": "0xdA22293aa75E005f7A6411a85f5aE053eBAfd3a9",
      "value": "0",
      "blockNumber": 40933198,
      "timeStamp": 1776368934
    },
    {
      "hash": "0x5db93708d3055bd5eb61c2c538bcc58035035c88934d0bb21d525d2a3ce4607e",
      "from": "0xdA22293aa75E005f7A6411a85f5aE053eBAfd3a9",
      "value": "0",
      "blockNumber": 40933193,
      "timeStamp": 1776368924
    },
    {
      "hash": "0x0bb3bce8f2e18338488f64afbda807dac66568afbf6ba9613ab2095e50394f78",
      "from": "0xdA22293aa75E005f7A6411a85f5aE053eBAfd3a9",
      "value": "0",
      "blockNumber": 40933188,
      "timeStamp": 1776368917
    },
    {
      "hash": "0x43c7b940acd05c18c661a20354e9656cf8a5439d1398cb29372dcd1e5e926f14",
      "from": "0xdA22293aa75E005f7A6411a85f5aE053eBAfd3a9",
      "value": "0",
      "blockNumber": 40933183,
      "timeStamp": 1776368906
    },
    {
      "hash": "0xe868bce5f03a98b350c1492001671586044a608e72f28249b7e970311bd3babb",
      "from": "0xdA22293aa75E005f7A6411a85f5aE053eBAfd3a9",
      "value": "0",
      "blockNumber": 40933178,
      "timeStamp": 1776368896
    },
    {
      "hash": "0xa1a332e35faa2bad305e905f9ad3e6465d965ee3158e0b976c88b10116858f66",
      "from": "0xdA22293aa75E005f7A6411a85f5aE053eBAfd3a9",
      "value": "0",
      "blockNumber": 40933173,
      "timeStamp": 1776368887
    },
    {
      "hash": "0x99545bc7526110f29ce5c3c293e8e1c6c028f7972f56db0ec7e207916cac0de2",
      "from": "0xdA22293aa75E005f7A6411a85f5aE053eBAfd3a9",
      "value": "0",
      "blockNumber": 40933168,
      "timeStamp": 1776368878
    },
    {
      "hash": "0x4f0c1873708f37d388639c958035c499fba17715ac6b378c4fa2bc517fc6dd22",
      "from": "0xdA22293aa75E005f7A6411a85f5aE053eBAfd3a9",
      "value": "0",
      "blockNumber": 40933163,
      "timeStamp": 1776368866
    }
  ],
  "lastUpdated": "2026-04-16T19:49:51.985Z",
  "dailyCounts": [
    {
      "date": "2026-04-16",
      "count": 2540
    },
    {
      "date": "2026-04-15",
      "count": 3021
    },
    {
      "date": "2026-04-14",
      "count": 2483
    },
    {
      "date": "2026-04-13",
      "count": 3220
    },
    {
      "date": "2026-04-12",
      "count": 2434
    },
    {
      "date": "2026-04-11",
      "count": 3127
    },
    {
      "date": "2026-04-10",
      "count": 2229
    },
    {
      "date": "2026-04-09",
      "count": 3312
    },
    {
      "date": "2026-04-08",
      "count": 3225
    },
    {
      "date": "2026-04-07",
      "count": 3153
    },
    {
      "date": "2026-04-06",
      "count": 3218
    },
    {
      "date": "2026-04-05",
      "count": 3369
    },
    {
      "date": "2026-04-04",
      "count": 2496
    },
    {
      "date": "2026-04-03",
      "count": 2463
    },
    {
      "date": "2026-04-02",
      "count": 3336
    },
    {
      "date": "2026-04-01",
      "count": 2442
    },
    {
      "date": "2026-03-31",
      "count": 3204
    },
    {
      "date": "2026-03-30",
      "count": 3093
    },
    {
      "date": "2026-03-29",
      "count": 3068
    },
    {
      "date": "2026-03-28",
      "count": 3289
    },
    {
      "date": "2026-03-27",
      "count": 2645
    },
    {
      "date": "2026-03-26",
      "count": 3026
    },
    {
      "date": "2026-03-25",
      "count": 3180
    },
    {
      "date": "2026-03-24",
      "count": 2980
    },
    {
      "date": "2026-03-23",
      "count": 3145
    },
    {
      "date": "2026-03-22",
      "count": 2196
    },
    {
      "date": "2026-03-21",
      "count": 2700
    },
    {
      "date": "2026-03-20",
      "count": 2389
    },
    {
      "date": "2026-03-19",
      "count": 2253
    },
    {
      "date": "2026-03-18",
      "count": 2412
    }
  ]
}