{
  "total": 130307,
  "last24h": 8741,
  "recentTxs": [
    {
      "hash": "0x9b9899d767045ce8ec7fa0d6c0e46376800600fd40850638827afecc3b26a3e1",
      "from": "0x94C62818aAdAE677878aC16fE649716020e1946A",
      "value": "0",
      "blockNumber": 39270751,
      "timeStamp": 1773349493
    },
    {
      "hash": "0xa48767a73d667bcbe4cf55bbfbe30e53b119327ee25e75159790ddfd9780f150",
      "from": "0x0d0241e2dD932E159F1016545c56636940033Bd9",
      "value": "0",
      "blockNumber": 39270739,
      "timeStamp": 1773349465
    },
    {
      "hash": "0xb280cc961cd567c17721e74dd5e2d0b54a01fbffd5103842e52658517e4a8647",
      "from": "0x55B01aaE298841142450C2426FD4B02B3eEd5028",
      "value": "0",
      "blockNumber": 39270723,
      "timeStamp": 1773349434
    },
    {
      "hash": "0xcca38f6f884f72dbb6f3c2a5a4068e505db283938725d900f0bd6389b8efb1df",
      "from": "0x55B01aaE298841142450C2426FD4B02B3eEd5028",
      "value": "0",
      "blockNumber": 39270720,
      "timeStamp": 1773349428
    },
    {
      "hash": "0xec4cf38513f7519215f901c41d1b720bc257b22d28f132ae054934b468acb2c2",
      "from": "0xF696123defD0471a96eb437765a581fb7c769d2c",
      "value": "0",
      "blockNumber": 39270708,
      "timeStamp": 1773349409
    },
    {
      "hash": "0x7076deacd9eafc1bea40df84564cc953114b5f950218ef643f21bd74eb9aaad5",
      "from": "0xc369633750E0FCCECe931261B50C005b7Bb2596A",
      "value": "0",
      "blockNumber": 39270696,
      "timeStamp": 1773349391
    },
    {
      "hash": "0x738561d1d2de6f7ca3ee419e1c5da9a10ae71b5cc62b1d9ba18458d17d8df07c",
      "from": "0x08346858795c92384889c6941F883Fb3D5b86AFd",
      "value": "0",
      "blockNumber": 39270685,
      "timeStamp": 1773349374
    },
    {
      "hash": "0xe5b25788998b17ee34c1a1ae452813be06a8d4f3dbf04b5c014f54b6ad70b303",
      "from": "0x24228d3B21870dfad6BA017A96f59B0AAF9785d1",
      "value": "0",
      "blockNumber": 39270667,
      "timeStamp": 1773349344
    },
    {
      "hash": "0x7498faf57d8406e0908f5b0e44a2a720e822f7dd909734f1242f53bc59e51eb8",
      "from": "0x24228d3B21870dfad6BA017A96f59B0AAF9785d1",
      "value": "0",
      "blockNumber": 39270662,
      "timeStamp": 1773349337
    },
    {
      "hash": "0xc29287fd857bc80d627adc8853969464275f1cb4effffab457f23130a69b53c8",
      "from": "0x8fF49E10E8A47Aa8441ad0C4bD571467E773D108",
      "value": "0",
      "blockNumber": 39270654,
      "timeStamp": 1773349319
    }
  ],
  "lastUpdated": "2026-03-12T21:05:25.698Z",
  "dailyCounts": [
    {
      "date": "2026-03-12",
      "count": 3965
    },
    {
      "date": "2026-03-11",
      "count": 4776
    },
    {
      "date": "2026-03-10",
      "count": 4558
    },
    {
      "date": "2026-03-09",
      "count": 4327
    },
    {
      "date": "2026-03-08",
      "count": 4579
    },
    {
      "date": "2026-03-07",
      "count": 6659
    },
    {
      "date": "2026-03-06",
      "count": 6501
    },
    {
      "date": "2026-03-05",
      "count": 6304
    },
    {
      "date": "2026-03-04",
      "count": 5961
    },
    {
      "date": "2026-03-03",
      "count": 4897
    },
    {
      "date": "2026-03-02",
      "count": 3020
    },
    {
      "date": "2026-03-01",
      "count": 6760
    },
    {
      "date": "2026-02-28",
      "count": 6730
    },
    {
      "date": "2026-02-27",
      "count": 6408
    },
    {
      "date": "2026-02-26",
      "count": 6161
    },
    {
      "date": "2026-02-25",
      "count": 6542
    },
    {
      "date": "2026-02-24",
      "count": 6522
    },
    {
      "date": "2026-02-23",
      "count": 6471
    },
    {
      "date": "2026-02-22",
      "count": 7229
    },
    {
      "date": "2026-02-21",
      "count": 7450
    },
    {
      "date": "2026-02-20",
      "count": 6983
    },
    {
      "date": "2026-02-19",
      "count": 7078
    }
  ]
}