{
  "total": 286884,
  "last24h": 3630,
  "recentTxs": [
    {
      "hash": "0x03f7eddc5d7592657f738a2e767e88a58756bb64505236373e4a520d96a1ae33",
      "from": "0xdA22293aa75E005f7A6411a85f5aE053eBAfd3a9",
      "value": "0",
      "blockNumber": 43537567,
      "timeStamp": 1780957633
    },
    {
      "hash": "0xc958b22eac6de8b462c9b3c8f2b989ff15a595806408b64d33b67536cdab39eb",
      "from": "0xdA22293aa75E005f7A6411a85f5aE053eBAfd3a9",
      "value": "0",
      "blockNumber": 43537557,
      "timeStamp": 1780957617
    },
    {
      "hash": "0xe04b3e6161186b49cbedec427281adbb6be88427672549936174333d3deb9aeb",
      "from": "0xdA22293aa75E005f7A6411a85f5aE053eBAfd3a9",
      "value": "0",
      "blockNumber": 43537552,
      "timeStamp": 1780957605
    },
    {
      "hash": "0x9e80f5dd07667ebb7e17bed9fb3e0970736727a28ff1042c0fc6b8f044bb673b",
      "from": "0xdA22293aa75E005f7A6411a85f5aE053eBAfd3a9",
      "value": "0",
      "blockNumber": 43537546,
      "timeStamp": 1780957596
    },
    {
      "hash": "0x09e133f7b10de4af91617035ed29b3b86e18edc9ee0877334c0a2d122df7c8b7",
      "from": "0xdA22293aa75E005f7A6411a85f5aE053eBAfd3a9",
      "value": "0",
      "blockNumber": 43537540,
      "timeStamp": 1780957587
    },
    {
      "hash": "0x0f1b411cefdb0013e511de521130e54689c473ff981c42dbf6c0caa1334cdbbc",
      "from": "0xdA22293aa75E005f7A6411a85f5aE053eBAfd3a9",
      "value": "0",
      "blockNumber": 43537535,
      "timeStamp": 1780957579
    },
    {
      "hash": "0x5a24705fc6899b6160946aea0ca05957b05a18eefd033aaf951a0ad9b66f1ede",
      "from": "0xdA22293aa75E005f7A6411a85f5aE053eBAfd3a9",
      "value": "0",
      "blockNumber": 43537530,
      "timeStamp": 1780957563
    },
    {
      "hash": "0x8db85a427a5e1c3da0a3e3c7603cd7887c677c05f559c8a56d9e9a6ea6923c3d",
      "from": "0xdA22293aa75E005f7A6411a85f5aE053eBAfd3a9",
      "value": "0",
      "blockNumber": 43537523,
      "timeStamp": 1780957553
    },
    {
      "hash": "0x7dac1926f56c84dc31d2b578fa1d0640f153e31db8bdd6275f22fd4c36aa3314",
      "from": "0xdA22293aa75E005f7A6411a85f5aE053eBAfd3a9",
      "value": "0",
      "blockNumber": 43537517,
      "timeStamp": 1780957540
    },
    {
      "hash": "0xd7f8972a91198d948ef8a55ccffd0a5d44a5ff1075b11b088cbacc3d1ad481e7",
      "from": "0xdA22293aa75E005f7A6411a85f5aE053eBAfd3a9",
      "value": "0",
      "blockNumber": 43537510,
      "timeStamp": 1780957531
    }
  ],
  "lastUpdated": "2026-06-08T22:42:02.728Z",
  "dailyCounts": [
    {
      "date": "2026-06-08",
      "count": 1609
    },
    {
      "date": "2026-06-07",
      "count": 2021
    },
    {
      "date": "2026-06-06",
      "count": 1949
    },
    {
      "date": "2026-06-05",
      "count": 2034
    },
    {
      "date": "2026-06-04",
      "count": 2067
    },
    {
      "date": "2026-06-03",
      "count": 2082
    },
    {
      "date": "2026-06-02",
      "count": 1946
    },
    {
      "date": "2026-06-01",
      "count": 2093
    },
    {
      "date": "2026-05-31",
      "count": 2375
    },
    {
      "date": "2026-05-30",
      "count": 2362
    },
    {
      "date": "2026-05-29",
      "count": 2453
    },
    {
      "date": "2026-05-28",
      "count": 2894
    },
    {
      "date": "2026-05-27",
      "count": 2148
    },
    {
      "date": "2026-05-26",
      "count": 2112
    },
    {
      "date": "2026-05-25",
      "count": 2219
    },
    {
      "date": "2026-05-24",
      "count": 2241
    },
    {
      "date": "2026-05-23",
      "count": 2139
    },
    {
      "date": "2026-05-22",
      "count": 2469
    },
    {
      "date": "2026-05-21",
      "count": 2341
    },
    {
      "date": "2026-05-20",
      "count": 3032
    },
    {
      "date": "2026-05-19",
      "count": 3198
    },
    {
      "date": "2026-05-18",
      "count": 2414
    },
    {
      "date": "2026-05-17",
      "count": 2462
    },
    {
      "date": "2026-05-16",
      "count": 3143
    },
    {
      "date": "2026-05-15",
      "count": 2559
    },
    {
      "date": "2026-05-14",
      "count": 2360
    },
    {
      "date": "2026-05-13",
      "count": 3153
    },
    {
      "date": "2026-05-12",
      "count": 2358
    },
    {
      "date": "2026-05-11",
      "count": 3015
    },
    {
      "date": "2026-05-10",
      "count": 2377
    }
  ]
}