{
  "total": 243867,
  "last24h": 6665,
  "recentTxs": [
    {
      "hash": "0xd7aa4ac543808530f1d1dd5a186d78ad1fdb9413285ebe9dc0e75633e2d466bb",
      "from": "0x2d2A1DB674a6Eb93603F8ae49aC193b8e2f0bBB1",
      "value": "0",
      "blockNumber": 40434142,
      "timeStamp": 1775456713
    },
    {
      "hash": "0x25078a7921f42a97fd4e447082c490fa0b2a3e42ffd021cafbd813c7b6f60778",
      "from": "0x90C8B973Ac31372695a3312155f146287f7c3530",
      "value": "0",
      "blockNumber": 40434124,
      "timeStamp": 1775456685
    },
    {
      "hash": "0x1818eb088c34f7423cc1f8547b28a81fc72b6f827070a2996caf23204d2e8ec4",
      "from": "0x90C8B973Ac31372695a3312155f146287f7c3530",
      "value": "0",
      "blockNumber": 40434121,
      "timeStamp": 1775456680
    },
    {
      "hash": "0xeda9aa545a0c34d33ef9595f79587193999a10022c778d7d07889afefe5da8e6",
      "from": "0xFcbBc891E69F1a480D3e964409F81c9a52410DE6",
      "value": "0",
      "blockNumber": 40434113,
      "timeStamp": 1775456667
    },
    {
      "hash": "0xc564c2149b65fcb116724cf118e133e75c1909079d0dcd061b4da22d1e992b23",
      "from": "0xd8208Dc194D8e7d65Ccce206040310daa6239f98",
      "value": "0",
      "blockNumber": 40434104,
      "timeStamp": 1775456653
    },
    {
      "hash": "0x08f41d919bfc0b500af9225a83aa7c5827dfa31f63c77b384ea4198c90be8149",
      "from": "0x0A9bAc56C9e7Fe581975c5147e45Dae7d52Bce48",
      "value": "0",
      "blockNumber": 40434097,
      "timeStamp": 1775456640
    },
    {
      "hash": "0xb3b2e23e137263883c15e09aa7a47e663617f4fcafefede6d6a2ad104bb6aa63",
      "from": "0x0Cea210cc826888D7c20BB1A5507AC7bf0802472",
      "value": "0",
      "blockNumber": 40434084,
      "timeStamp": 1775456610
    },
    {
      "hash": "0xaacd654eb26344d46e3add880f6114809ff7179cba00fed4e15a9f780c2a0fd4",
      "from": "0x0Cea210cc826888D7c20BB1A5507AC7bf0802472",
      "value": "0",
      "blockNumber": 40434081,
      "timeStamp": 1775456605
    },
    {
      "hash": "0x8e604de874f368465d4b7aa5977d8157f5e200026cd24e9c17550f79f7f61903",
      "from": "0xb10125c5670d3EF38a81Bd44998E1aa91d1AE939",
      "value": "0",
      "blockNumber": 40434072,
      "timeStamp": 1775456592
    },
    {
      "hash": "0xe019392c9edd46eaafca4b3fe2d627586d363c4c8fafd189bcd37b6d3168bf97",
      "from": "0x948AA535ABE068f61029d6a787728848fbf56b3D",
      "value": "0",
      "blockNumber": 40434063,
      "timeStamp": 1775456575
    }
  ],
  "lastUpdated": "2026-04-06T06:26:48.137Z",
  "dailyCounts": [
    {
      "date": "2026-04-06",
      "count": 1309
    },
    {
      "date": "2026-04-05",
      "count": 5356
    },
    {
      "date": "2026-04-04",
      "count": 5300
    },
    {
      "date": "2026-04-03",
      "count": 5324
    },
    {
      "date": "2026-04-02",
      "count": 5185
    },
    {
      "date": "2026-04-01",
      "count": 5215
    },
    {
      "date": "2026-03-31",
      "count": 5120
    },
    {
      "date": "2026-03-30",
      "count": 4753
    },
    {
      "date": "2026-03-29",
      "count": 4977
    },
    {
      "date": "2026-03-28",
      "count": 4773
    },
    {
      "date": "2026-03-27",
      "count": 4763
    },
    {
      "date": "2026-03-26",
      "count": 4312
    },
    {
      "date": "2026-03-25",
      "count": 4521
    },
    {
      "date": "2026-03-24",
      "count": 4326
    },
    {
      "date": "2026-03-23",
      "count": 4480
    },
    {
      "date": "2026-03-22",
      "count": 4246
    },
    {
      "date": "2026-03-21",
      "count": 4282
    },
    {
      "date": "2026-03-20",
      "count": 4174
    },
    {
      "date": "2026-03-19",
      "count": 4182
    },
    {
      "date": "2026-03-18",
      "count": 4434
    },
    {
      "date": "2026-03-17",
      "count": 4407
    },
    {
      "date": "2026-03-16",
      "count": 4276
    },
    {
      "date": "2026-03-15",
      "count": 4437
    },
    {
      "date": "2026-03-14",
      "count": 4433
    },
    {
      "date": "2026-03-13",
      "count": 4360
    },
    {
      "date": "2026-03-12",
      "count": 4580
    },
    {
      "date": "2026-03-11",
      "count": 4776
    },
    {
      "date": "2026-03-10",
      "count": 4558
    },
    {
      "date": "2026-03-09",
      "count": 4327
    },
    {
      "date": "2026-03-08",
      "count": 4579
    }
  ]
}