{
  "total": 146830,
  "last24h": 7115,
  "recentTxs": [
    {
      "hash": "0xbd6fcfc1a74d17ca6be24327965201b509f3ec28176fec4d7df1c438dc499877",
      "from": "0xc8f256bEA1Ec52B08A3320D8D4EAA58c0A5B15d2",
      "value": "0",
      "blockNumber": 39447660,
      "timeStamp": 1773674363
    },
    {
      "hash": "0xd942212310e5d9270a70257c1d4c8409c41f02166a272ca3ff441fd2df08188f",
      "from": "0xc8f256bEA1Ec52B08A3320D8D4EAA58c0A5B15d2",
      "value": "0",
      "blockNumber": 39447656,
      "timeStamp": 1773674354
    },
    {
      "hash": "0xf816198c37fc1c590ec4547d937a5477b783244694d38bbf8729b87b482288bb",
      "from": "0xAC2505D2Bcae40e5c6f03A79006c900C12cE3E0e",
      "value": "0",
      "blockNumber": 39447648,
      "timeStamp": 1773674336
    },
    {
      "hash": "0xccb990659214e68fcbed80b0e8f759848994730de78ddf8363806febe3e0b491",
      "from": "0xa36144f1e17035BC1b09885E2aB3d7E130c9034a",
      "value": "0",
      "blockNumber": 39447636,
      "timeStamp": 1773674317
    },
    {
      "hash": "0x8da389536fbd50bc4e8dc25d9aa563ae7f01ad716381d521fd0b48ef833d6cde",
      "from": "0x0E92349b45caAeaF8A7e9C2e14BbAE75ed9b6202",
      "value": "0",
      "blockNumber": 39447626,
      "timeStamp": 1773674300
    },
    {
      "hash": "0xa822204c65c1b47c64671b604415dcd31a27fca37808ffaf7a7e54891069145b",
      "from": "0xeb1c7C3D4cb6Ee3e59D1aC3054Ced40E84DAAEE4",
      "value": "0",
      "blockNumber": 39447605,
      "timeStamp": 1773674269
    },
    {
      "hash": "0xd8d902b027bbb0067e1b3ef036ab8a530902f8c04839d49bbf480aa64784e0c3",
      "from": "0xeb1c7C3D4cb6Ee3e59D1aC3054Ced40E84DAAEE4",
      "value": "0",
      "blockNumber": 39447601,
      "timeStamp": 1773674263
    },
    {
      "hash": "0x0dfc39573c1b83b28e2417b58e6137522de06385decd8dd4e08d578ea6356437",
      "from": "0xA9Aa5753Cd563e11EDd515635C492a6abF6372eb",
      "value": "0",
      "blockNumber": 39447591,
      "timeStamp": 1773674246
    },
    {
      "hash": "0x463dbf7f321970f2ddc6864ec1d60163f537010f8ca8ec616424d49365256d69",
      "from": "0x42B232862dA5970c91626dEC775Ab3048692006D",
      "value": "0",
      "blockNumber": 39447582,
      "timeStamp": 1773674226
    },
    {
      "hash": "0xa813565bd22857f7412f7db6da2faa6b2e834329d9699e08ddad1525d68c3d24",
      "from": "0x900b2B92b912988223A486440438eF94350E5672",
      "value": "0",
      "blockNumber": 39447570,
      "timeStamp": 1773674208
    }
  ],
  "lastUpdated": "2026-03-16T15:19:48.005Z",
  "dailyCounts": [
    {
      "date": "2026-03-16",
      "count": 2678
    },
    {
      "date": "2026-03-15",
      "count": 4437
    },
    {
      "date": "2026-03-14",
      "count": 4433
    },
    {
      "date": "2026-03-13",
      "count": 4360
    },
    {
      "date": "2026-03-12",
      "count": 4580
    },
    {
      "date": "2026-03-11",
      "count": 4776
    },
    {
      "date": "2026-03-10",
      "count": 4558
    },
    {
      "date": "2026-03-09",
      "count": 4327
    },
    {
      "date": "2026-03-08",
      "count": 4579
    },
    {
      "date": "2026-03-07",
      "count": 6659
    },
    {
      "date": "2026-03-06",
      "count": 6501
    },
    {
      "date": "2026-03-05",
      "count": 6304
    },
    {
      "date": "2026-03-04",
      "count": 5961
    },
    {
      "date": "2026-03-03",
      "count": 4897
    },
    {
      "date": "2026-03-02",
      "count": 3020
    },
    {
      "date": "2026-03-01",
      "count": 6760
    },
    {
      "date": "2026-02-28",
      "count": 6730
    },
    {
      "date": "2026-02-27",
      "count": 6408
    },
    {
      "date": "2026-02-26",
      "count": 6161
    },
    {
      "date": "2026-02-25",
      "count": 6542
    },
    {
      "date": "2026-02-24",
      "count": 6522
    },
    {
      "date": "2026-02-23",
      "count": 6471
    },
    {
      "date": "2026-02-22",
      "count": 7229
    },
    {
      "date": "2026-02-21",
      "count": 7450
    },
    {
      "date": "2026-02-20",
      "count": 6983
    },
    {
      "date": "2026-02-19",
      "count": 7078
    }
  ]
}