{
  "total": 168396,
  "last24h": 4681,
  "recentTxs": [
    {
      "hash": "0x02aa80cdfb8331cf8438ccf2323f500578b64aabcbd03486c8f2bda4205acebe",
      "from": "0xdA22293aa75E005f7A6411a85f5aE053eBAfd3a9",
      "value": "0",
      "blockNumber": 41175481,
      "timeStamp": 1776809247
    },
    {
      "hash": "0x343396011c2879b2a98dfe60b75574cc163d863affd8eb63ebff60944311942f",
      "from": "0xdA22293aa75E005f7A6411a85f5aE053eBAfd3a9",
      "value": "0",
      "blockNumber": 41175466,
      "timeStamp": 1776809224
    },
    {
      "hash": "0x8d7c69b554a7b24049f3bfc79dc8088b1d3ca245466fbc930d890cbc0143741e",
      "from": "0xdA22293aa75E005f7A6411a85f5aE053eBAfd3a9",
      "value": "0",
      "blockNumber": 41175461,
      "timeStamp": 1776809214
    },
    {
      "hash": "0x3f1344bf85ab5fb8fa28efb9265d75cfad211ef0b0de1130b38c34cbe300729c",
      "from": "0xdA22293aa75E005f7A6411a85f5aE053eBAfd3a9",
      "value": "0",
      "blockNumber": 41175456,
      "timeStamp": 1776809205
    },
    {
      "hash": "0xc55a4d1cb1b1775cee14c74e1a1598519e48d2e18d02d3cc753bacf02b05bd6f",
      "from": "0xdA22293aa75E005f7A6411a85f5aE053eBAfd3a9",
      "value": "0",
      "blockNumber": 41175451,
      "timeStamp": 1776809198
    },
    {
      "hash": "0x258dca834f7c8c761abc76050c09c00922f2e92d8d7eb7772bc8e69d217979f8",
      "from": "0xdA22293aa75E005f7A6411a85f5aE053eBAfd3a9",
      "value": "0",
      "blockNumber": 41175446,
      "timeStamp": 1776809190
    },
    {
      "hash": "0x0601304b7f308bb4d2d63f6e819c446f49f03996776ab8e6a7bbc7abde88860b",
      "from": "0xdA22293aa75E005f7A6411a85f5aE053eBAfd3a9",
      "value": "0",
      "blockNumber": 41175441,
      "timeStamp": 1776809182
    },
    {
      "hash": "0x3727eaff62621094f2b714427776534f22f27c2dd92ee6ba4a537c204db297a6",
      "from": "0xdA22293aa75E005f7A6411a85f5aE053eBAfd3a9",
      "value": "0",
      "blockNumber": 41175436,
      "timeStamp": 1776809174
    },
    {
      "hash": "0xcdd23cc758c8c1ba92091cb63170e34010e4f70970f339e1baf110b5e885f9d7",
      "from": "0xdA22293aa75E005f7A6411a85f5aE053eBAfd3a9",
      "value": "0",
      "blockNumber": 41175431,
      "timeStamp": 1776809167
    },
    {
      "hash": "0x2882ba2b26b011139ce080a6573eb78b5dabe0ee346fd26c73f7758189d3ce2e",
      "from": "0xdA22293aa75E005f7A6411a85f5aE053eBAfd3a9",
      "value": "0",
      "blockNumber": 41175426,
      "timeStamp": 1776809158
    }
  ],
  "lastUpdated": "2026-04-21T22:08:14.936Z",
  "dailyCounts": [
    {
      "date": "2026-04-21",
      "count": 2300
    },
    {
      "date": "2026-04-20",
      "count": 2381
    },
    {
      "date": "2026-04-19",
      "count": 2508
    },
    {
      "date": "2026-04-18",
      "count": 2553
    },
    {
      "date": "2026-04-17",
      "count": 3151
    },
    {
      "date": "2026-04-16",
      "count": 3169
    },
    {
      "date": "2026-04-15",
      "count": 3021
    },
    {
      "date": "2026-04-14",
      "count": 2483
    },
    {
      "date": "2026-04-13",
      "count": 3220
    },
    {
      "date": "2026-04-12",
      "count": 2434
    },
    {
      "date": "2026-04-11",
      "count": 3127
    },
    {
      "date": "2026-04-10",
      "count": 2229
    },
    {
      "date": "2026-04-09",
      "count": 3312
    },
    {
      "date": "2026-04-08",
      "count": 3225
    },
    {
      "date": "2026-04-07",
      "count": 3153
    },
    {
      "date": "2026-04-06",
      "count": 3218
    },
    {
      "date": "2026-04-05",
      "count": 3369
    },
    {
      "date": "2026-04-04",
      "count": 2496
    },
    {
      "date": "2026-04-03",
      "count": 2463
    },
    {
      "date": "2026-04-02",
      "count": 3336
    },
    {
      "date": "2026-04-01",
      "count": 2442
    },
    {
      "date": "2026-03-31",
      "count": 3204
    },
    {
      "date": "2026-03-30",
      "count": 3093
    },
    {
      "date": "2026-03-29",
      "count": 3068
    },
    {
      "date": "2026-03-28",
      "count": 3289
    },
    {
      "date": "2026-03-27",
      "count": 2645
    },
    {
      "date": "2026-03-26",
      "count": 3026
    },
    {
      "date": "2026-03-25",
      "count": 3180
    },
    {
      "date": "2026-03-24",
      "count": 2980
    },
    {
      "date": "2026-03-23",
      "count": 3145
    }
  ]
}