{
  "total": 157773,
  "last24h": 5439,
  "recentTxs": [
    {
      "hash": "0xc4166c009f089659ec3737d8b66044d70f2cea7ffb08dea04ff0978eefb207d7",
      "from": "0xdA22293aa75E005f7A6411a85f5aE053eBAfd3a9",
      "value": "0",
      "blockNumber": 40978414,
      "timeStamp": 1776452576
    },
    {
      "hash": "0xac4f518e7f61cf02c268990e4f4ff5c255229fa0324f82e6620e1125f6e8354d",
      "from": "0xdA22293aa75E005f7A6411a85f5aE053eBAfd3a9",
      "value": "0",
      "blockNumber": 40978406,
      "timeStamp": 1776452562
    },
    {
      "hash": "0x6cf18748ba5fd158bcb43c4ca58dbcfbcc5ec1b5c2e382927ce4a115949fa238",
      "from": "0xdA22293aa75E005f7A6411a85f5aE053eBAfd3a9",
      "value": "0",
      "blockNumber": 40978400,
      "timeStamp": 1776452551
    },
    {
      "hash": "0x3386c5b6e709fa8e62f89f5472cdfc168491200aad33c2eee343ac43dab13ec0",
      "from": "0xdA22293aa75E005f7A6411a85f5aE053eBAfd3a9",
      "value": "0",
      "blockNumber": 40978392,
      "timeStamp": 1776452539
    },
    {
      "hash": "0xc0380eb5a8d58a3a178ac8854199cafdad3456d8d10b11deb2c39174455bada7",
      "from": "0xdA22293aa75E005f7A6411a85f5aE053eBAfd3a9",
      "value": "0",
      "blockNumber": 40978386,
      "timeStamp": 1776452527
    },
    {
      "hash": "0x54cccfe7f3fe5f7636f859e933033d2c7d74de5a6de5b450c5a798a18de40dd4",
      "from": "0xdA22293aa75E005f7A6411a85f5aE053eBAfd3a9",
      "value": "0",
      "blockNumber": 40978381,
      "timeStamp": 1776452515
    },
    {
      "hash": "0xbc97801cb2b526ee333c61b672e513bed048b603877bf32e5387544884e34397",
      "from": "0xdA22293aa75E005f7A6411a85f5aE053eBAfd3a9",
      "value": "0",
      "blockNumber": 40978374,
      "timeStamp": 1776452500
    },
    {
      "hash": "0x8fcc83703954fe93b6f658a1375a1721ccd88f63d9bb3bf1f49f94ae0348e01a",
      "from": "0xdA22293aa75E005f7A6411a85f5aE053eBAfd3a9",
      "value": "0",
      "blockNumber": 40978368,
      "timeStamp": 1776452485
    },
    {
      "hash": "0xa02c23ec15cbb0fa078f8edb363d60138cf954509261379f833b96ad03dc62e6",
      "from": "0xdA22293aa75E005f7A6411a85f5aE053eBAfd3a9",
      "value": "0",
      "blockNumber": 40978360,
      "timeStamp": 1776452472
    },
    {
      "hash": "0x115c4d27ee3b180136648c775816d82ce369e9b1d639f291fc26abe4291e15ca",
      "from": "0xdA22293aa75E005f7A6411a85f5aE053eBAfd3a9",
      "value": "0",
      "blockNumber": 40978354,
      "timeStamp": 1776452461
    }
  ],
  "lastUpdated": "2026-04-17T19:03:25.288Z",
  "dailyCounts": [
    {
      "date": "2026-04-17",
      "count": 2270
    },
    {
      "date": "2026-04-16",
      "count": 3169
    },
    {
      "date": "2026-04-15",
      "count": 3021
    },
    {
      "date": "2026-04-14",
      "count": 2483
    },
    {
      "date": "2026-04-13",
      "count": 3220
    },
    {
      "date": "2026-04-12",
      "count": 2434
    },
    {
      "date": "2026-04-11",
      "count": 3127
    },
    {
      "date": "2026-04-10",
      "count": 2229
    },
    {
      "date": "2026-04-09",
      "count": 3312
    },
    {
      "date": "2026-04-08",
      "count": 3225
    },
    {
      "date": "2026-04-07",
      "count": 3153
    },
    {
      "date": "2026-04-06",
      "count": 3218
    },
    {
      "date": "2026-04-05",
      "count": 3369
    },
    {
      "date": "2026-04-04",
      "count": 2496
    },
    {
      "date": "2026-04-03",
      "count": 2463
    },
    {
      "date": "2026-04-02",
      "count": 3336
    },
    {
      "date": "2026-04-01",
      "count": 2442
    },
    {
      "date": "2026-03-31",
      "count": 3204
    },
    {
      "date": "2026-03-30",
      "count": 3093
    },
    {
      "date": "2026-03-29",
      "count": 3068
    },
    {
      "date": "2026-03-28",
      "count": 3289
    },
    {
      "date": "2026-03-27",
      "count": 2645
    },
    {
      "date": "2026-03-26",
      "count": 3026
    },
    {
      "date": "2026-03-25",
      "count": 3180
    },
    {
      "date": "2026-03-24",
      "count": 2980
    },
    {
      "date": "2026-03-23",
      "count": 3145
    },
    {
      "date": "2026-03-22",
      "count": 2196
    },
    {
      "date": "2026-03-21",
      "count": 2700
    },
    {
      "date": "2026-03-20",
      "count": 2389
    },
    {
      "date": "2026-03-19",
      "count": 2253
    }
  ]
}