{
  "total": 439497,
  "last24h": 9980,
  "recentTxs": [
    {
      "hash": "0xc31465a352a99432f2ff35c8706f73eec9eb9969138f434e1b97a74a2e8c65db",
      "from": "0xC8916f4eAd0566996763feDe37926666012a22Bb",
      "value": "0",
      "blockNumber": 42345744,
      "timeStamp": 1778969254
    },
    {
      "hash": "0x2a027ec94b875d4a475135fabe62d6ba2383d2d576416fbcab22e98cfb1853d0",
      "from": "0x86433b0635B3047305F2dCDD73aF1575D6aA2068",
      "value": "0",
      "blockNumber": 42345725,
      "timeStamp": 1778969221
    },
    {
      "hash": "0x628c44a89bc18d091ef9e7a4296a20e9292cce394fb31b0c41bec825892b5755",
      "from": "0x86433b0635B3047305F2dCDD73aF1575D6aA2068",
      "value": "0",
      "blockNumber": 42345719,
      "timeStamp": 1778969211
    },
    {
      "hash": "0x5659863d8eb6b282600b33e2fe0ffd4eed9f3e133a3152e7f9161c900f5dd3e8",
      "from": "0x500180Dcc234bf975bfeFff2FB0889E994d11bFA",
      "value": "0",
      "blockNumber": 42345711,
      "timeStamp": 1778969198
    },
    {
      "hash": "0x229b09980fb3dcddd7bca16349a95db4c7677f6240f8df9d5d445759daf50704",
      "from": "0x8986716e36AFca055f342c5D34ca25bBea087100",
      "value": "0",
      "blockNumber": 42345705,
      "timeStamp": 1778969184
    },
    {
      "hash": "0xe44b899ec167eaa8b1770997e223d8a5a7444fcffc0f66394b92153bd85655f5",
      "from": "0xE3d3eeAF0CFc3d1E25b8470daacAd3340bb6F934",
      "value": "0",
      "blockNumber": 42345697,
      "timeStamp": 1778969169
    },
    {
      "hash": "0xf860daa1033cdcfd5f097e17c3d42262241cb001efe3cdc547d9042d37baf490",
      "from": "0xb9E1A06549580776a9eed7c92C98DA4CCfcC0850",
      "value": "0",
      "blockNumber": 42345688,
      "timeStamp": 1778969144
    },
    {
      "hash": "0xea9a9d169bc2539f6853b1eac357bc66267aaf3b5526d3f0084d8e8c0a93793a",
      "from": "0xb9E1A06549580776a9eed7c92C98DA4CCfcC0850",
      "value": "0",
      "blockNumber": 42345684,
      "timeStamp": 1778969138
    },
    {
      "hash": "0x2269e66ef2718a74beb9263d76794f0189e66632ac7452773e3943ca20a53298",
      "from": "0xb0f733055B8DBcd74AF42889255892028A368e6B",
      "value": "0",
      "blockNumber": 42345677,
      "timeStamp": 1778969120
    },
    {
      "hash": "0x72e74d98652f4a49c866fe45c3ff47ea13e38842cb55475024bad293c47e4c31",
      "from": "0xcD32403fBa3455528b67690915A192C8f59735b7",
      "value": "0",
      "blockNumber": 42345667,
      "timeStamp": 1778969103
    }
  ],
  "lastUpdated": "2026-05-16T22:08:55.120Z",
  "dailyCounts": [
    {
      "date": "2026-05-16",
      "count": 4763
    },
    {
      "date": "2026-05-15",
      "count": 5217
    },
    {
      "date": "2026-05-14",
      "count": 5104
    },
    {
      "date": "2026-05-13",
      "count": 5034
    },
    {
      "date": "2026-05-12",
      "count": 5005
    },
    {
      "date": "2026-05-11",
      "count": 4870
    },
    {
      "date": "2026-05-10",
      "count": 4918
    },
    {
      "date": "2026-05-09",
      "count": 4991
    },
    {
      "date": "2026-05-08",
      "count": 5003
    },
    {
      "date": "2026-05-07",
      "count": 3914
    },
    {
      "date": "2026-05-06",
      "count": 3544
    },
    {
      "date": "2026-05-05",
      "count": 4592
    },
    {
      "date": "2026-05-04",
      "count": 3859
    },
    {
      "date": "2026-05-03",
      "count": 3940
    },
    {
      "date": "2026-05-02",
      "count": 3995
    },
    {
      "date": "2026-05-01",
      "count": 4211
    },
    {
      "date": "2026-04-30",
      "count": 4928
    },
    {
      "date": "2026-04-29",
      "count": 5097
    },
    {
      "date": "2026-04-28",
      "count": 5074
    },
    {
      "date": "2026-04-27",
      "count": 5021
    },
    {
      "date": "2026-04-26",
      "count": 5046
    },
    {
      "date": "2026-04-25",
      "count": 5115
    },
    {
      "date": "2026-04-24",
      "count": 5017
    },
    {
      "date": "2026-04-23",
      "count": 4670
    },
    {
      "date": "2026-04-22",
      "count": 4993
    },
    {
      "date": "2026-04-21",
      "count": 4999
    },
    {
      "date": "2026-04-20",
      "count": 4840
    },
    {
      "date": "2026-04-19",
      "count": 5019
    },
    {
      "date": "2026-04-18",
      "count": 4872
    },
    {
      "date": "2026-04-17",
      "count": 4597
    }
  ]
}